{
  "schemaVersion": "1.0",
  "repos": [
    {
      "repo": "dotnet-buildtools/image-builder",
      "images": [
        {
          "manifest": {
            "digest": "mcr.microsoft.com/dotnet-buildtools/image-builder@sha256:7b6051c35c31a2766949b22e6510083ca9d8bb83a71b621b272472b0a00f8d9e",
            "created": "2020-09-25T15:45:31.4358891Z",
            "sharedTags": [
              "831151"
            ]
          },
          "platforms": [
            {
              "dockerfile": "Dockerfile.linux",
              "simpleTags": [
                "linux-amd64-831151"
              ],
              "digest": "mcr.microsoft.com/dotnet-buildtools/image-builder@sha256:6efa58ed40dab0bab7cf9b41a6f083a47d0759b8975a1e8d81da817a3e11772d",
              "baseImageDigest": "mcr.microsoft.com/dotnet/core/runtime-deps@sha256:55eddd57e3e59af4418e786168b421004bd26a8286c9af62d89464aaca43ce79",
              "osType": "Linux",
              "osVersion": "Alpine",
              "architecture": "amd64",
              "created": "2020-09-25T15:34:01.8077848Z",
              "commitUrl": "https://github.com/dotnet/docker-tools/blob/9ddf6f77283b494a4fbab73c8376acfbd8e235be/Dockerfile.linux"
            },
            {
              "dockerfile": "Dockerfile.linux",
              "simpleTags": [
                "linux-arm64-831151"
              ],
              "digest": "mcr.microsoft.com/dotnet-buildtools/image-builder@sha256:1869a1b156b02be2001344a97881c83c4de3814200d288764636706a3c8236a2",
              "baseImageDigest": "mcr.microsoft.com/dotnet/core/runtime-deps@sha256:b3f08d8294e66c1e32c6fa5708b1a01ebae8e29f7346fef852dfe29b9ba482eb",
              "osType": "Linux",
              "osVersion": "Alpine",
              "architecture": "arm64",
              "created": "2020-09-25T15:35:44.823186Z",
              "commitUrl": "https://github.com/dotnet/docker-tools/blob/9ddf6f77283b494a4fbab73c8376acfbd8e235be/Dockerfile.linux"
            },
            {
              "dockerfile": "Dockerfile.windows",
              "simpleTags": [
                "windows-amd64-831151"
              ],
              "digest": "mcr.microsoft.com/dotnet-buildtools/image-builder@sha256:696f3ea8d5f2ddfc3d6575a933428d949387c6ad6b73eee88701594a3f93c295",
              "baseImageDigest": "mcr.microsoft.com/windows/nanoserver@sha256:2b783310e6c82de737e893abd53ae238ca56b5a96e2861558fb9a111d6691ddb",
              "osType": "Windows",
              "osVersion": "Windows Server 2019",
              "architecture": "amd64",
              "created": "2020-09-25T15:34:57.0591706Z",
              "commitUrl": "https://github.com/dotnet/docker-tools/blob/38bc667d2578111c83d03e12bd90db3f11df3080/Dockerfile.windows"
            }
          ]
        }
      ]
    }
  ]
}
