{
  "schemaVersion": "1.0",
  "repos": [
    {
      "repo": "dotnet-buildtools/image-builder",
      "images": [
        {
          "manifest": {
            "digest": "mcr.microsoft.com/dotnet-buildtools/image-builder@sha256:7934eeef598fd33eaa6a4819e53864942794136e44f2bd1fe8181c193aa877d5",
            "created": "2020-10-07T21:29:01.0622074Z",
            "sharedTags": [
              "844353"
            ]
          },
          "platforms": [
            {
              "dockerfile": "Dockerfile.linux",
              "simpleTags": [
                "linux-amd64-844353"
              ],
              "digest": "mcr.microsoft.com/dotnet-buildtools/image-builder@sha256:5cd7769d86128084b9b86c0b02f25f67a67f8f909c01379fa3eea1ca0ca1469b",
              "baseImageDigest": "mcr.microsoft.com/dotnet/core/runtime-deps@sha256:55eddd57e3e59af4418e786168b421004bd26a8286c9af62d89464aaca43ce79",
              "osType": "Linux",
              "osVersion": "Alpine",
              "architecture": "amd64",
              "created": "2020-10-07T21:19:19.0906724Z",
              "commitUrl": "https://github.com/dotnet/docker-tools/blob/9ddf6f77283b494a4fbab73c8376acfbd8e235be/Dockerfile.linux"
            },
            {
              "dockerfile": "Dockerfile.linux",
              "simpleTags": [
                "linux-arm64-844353"
              ],
              "digest": "mcr.microsoft.com/dotnet-buildtools/image-builder@sha256:f426f61f34a1df728ccb9d4835da30704afdeb5aacfa291ab5f0d0baa8ad9d0c",
              "baseImageDigest": "mcr.microsoft.com/dotnet/core/runtime-deps@sha256:b3f08d8294e66c1e32c6fa5708b1a01ebae8e29f7346fef852dfe29b9ba482eb",
              "osType": "Linux",
              "osVersion": "Alpine",
              "architecture": "arm64",
              "created": "2020-10-07T21:18:22.0629516Z",
              "commitUrl": "https://github.com/dotnet/docker-tools/blob/9ddf6f77283b494a4fbab73c8376acfbd8e235be/Dockerfile.linux"
            },
            {
              "dockerfile": "Dockerfile.windows",
              "simpleTags": [
                "windows-amd64-844353"
              ],
              "digest": "mcr.microsoft.com/dotnet-buildtools/image-builder@sha256:3d8daf1efdfa783187f010a5ee2c7f7c379e3ae91af6ac4ce161014a8f30c721",
              "baseImageDigest": "mcr.microsoft.com/windows/nanoserver@sha256:2b783310e6c82de737e893abd53ae238ca56b5a96e2861558fb9a111d6691ddb",
              "osType": "Windows",
              "osVersion": "Windows Server 2019",
              "architecture": "amd64",
              "created": "2020-10-07T21:19:31.8487042Z",
              "commitUrl": "https://github.com/dotnet/docker-tools/blob/38bc667d2578111c83d03e12bd90db3f11df3080/Dockerfile.windows"
            }
          ]
        }
      ]
    }
  ]
}
