{
  "schemaVersion": "1.0",
  "repos": [
    {
      "repo": "dotnet-buildtools/image-builder",
      "images": [
        {
          "manifest": {
            "digest": "mcr.microsoft.com/dotnet-buildtools/image-builder@sha256:791508a5d031b1161613d28264a8d96b5c3c4e4382a0e972e39d8ef65db87882",
            "created": "2020-09-16T21:18:52.8156622Z",
            "sharedTags": [
              "818185"
            ]
          },
          "platforms": [
            {
              "dockerfile": "Dockerfile.linux",
              "simpleTags": [
                "linux-amd64-818185"
              ],
              "digest": "mcr.microsoft.com/dotnet-buildtools/image-builder@sha256:601bb8155943a1e1d1c14ce0dcc23fac22cc84914f2254bab0cc6a550afd57cd",
              "baseImageDigest": "mcr.microsoft.com/dotnet/core/runtime-deps@sha256:55eddd57e3e59af4418e786168b421004bd26a8286c9af62d89464aaca43ce79",
              "osType": "Linux",
              "osVersion": "Alpine",
              "architecture": "amd64",
              "created": "2020-09-16T21:07:51.9199851Z",
              "commitUrl": "https://github.com/dotnet/docker-tools/blob/9ddf6f77283b494a4fbab73c8376acfbd8e235be/Dockerfile.linux"
            },
            {
              "dockerfile": "Dockerfile.linux",
              "simpleTags": [
                "linux-arm64-818185"
              ],
              "digest": "mcr.microsoft.com/dotnet-buildtools/image-builder@sha256:cd78b7afe66a10748c08036558586d1dca4e096d7d6fb0aaaeab2db3ee7a7599",
              "baseImageDigest": "mcr.microsoft.com/dotnet/core/runtime-deps@sha256:b3f08d8294e66c1e32c6fa5708b1a01ebae8e29f7346fef852dfe29b9ba482eb",
              "osType": "Linux",
              "osVersion": "Alpine",
              "architecture": "arm64",
              "created": "2020-09-16T21:09:48.2518Z",
              "commitUrl": "https://github.com/dotnet/docker-tools/blob/9ddf6f77283b494a4fbab73c8376acfbd8e235be/Dockerfile.linux"
            },
            {
              "dockerfile": "Dockerfile.windows",
              "simpleTags": [
                "windows-amd64-818185"
              ],
              "digest": "mcr.microsoft.com/dotnet-buildtools/image-builder@sha256:f1be0b997538c214189b06eb307681e9c50c3fdcc69dc1b048ff66580e7deba4",
              "baseImageDigest": "mcr.microsoft.com/windows/nanoserver@sha256:2b783310e6c82de737e893abd53ae238ca56b5a96e2861558fb9a111d6691ddb",
              "osType": "Windows",
              "osVersion": "Windows Server 2019",
              "architecture": "amd64",
              "created": "2020-09-16T21:09:22.5460801Z",
              "commitUrl": "https://github.com/dotnet/docker-tools/blob/38bc667d2578111c83d03e12bd90db3f11df3080/Dockerfile.windows"
            }
          ]
        }
      ]
    }
  ]
}
