{
  "schemaVersion": "1.0",
  "repos": [
    {
      "repo": "dotnet-buildtools/image-builder",
      "images": [
        {
          "manifest": {
            "digest": "mcr.microsoft.com/dotnet-buildtools/image-builder@sha256:c746e4e399228825d3deba98abd9de8b9be1525f24e44f3be106ca0fd7a32a07",
            "created": "2020-09-15T17:22:33.4897919Z",
            "sharedTags": [
              "816033"
            ]
          },
          "platforms": [
            {
              "dockerfile": "Dockerfile.linux",
              "simpleTags": [
                "linux-amd64-816033"
              ],
              "digest": "mcr.microsoft.com/dotnet-buildtools/image-builder@sha256:1cec6c21e147eb8b4555633149087c640e5b780d37c55d3e3276e80b26fc85d7",
              "baseImageDigest": "mcr.microsoft.com/dotnet/core/runtime-deps@sha256:55eddd57e3e59af4418e786168b421004bd26a8286c9af62d89464aaca43ce79",
              "osType": "Linux",
              "osVersion": "Alpine",
              "architecture": "amd64",
              "created": "2020-09-15T17:09:10.9587869Z",
              "commitUrl": "https://github.com/dotnet/docker-tools/blob/9ddf6f77283b494a4fbab73c8376acfbd8e235be/Dockerfile.linux"
            },
            {
              "dockerfile": "Dockerfile.linux",
              "simpleTags": [
                "linux-arm64-816033"
              ],
              "digest": "mcr.microsoft.com/dotnet-buildtools/image-builder@sha256:7b5ae0489db4b5a755465602ec1be1e675462aa1947650c0cb29c48d6d1032f6",
              "baseImageDigest": "mcr.microsoft.com/dotnet/core/runtime-deps@sha256:b3f08d8294e66c1e32c6fa5708b1a01ebae8e29f7346fef852dfe29b9ba482eb",
              "osType": "Linux",
              "osVersion": "Alpine",
              "architecture": "arm64",
              "created": "2020-09-15T17:10:16.7358084Z",
              "commitUrl": "https://github.com/dotnet/docker-tools/blob/9ddf6f77283b494a4fbab73c8376acfbd8e235be/Dockerfile.linux"
            },
            {
              "dockerfile": "Dockerfile.windows",
              "simpleTags": [
                "windows-amd64-816033"
              ],
              "digest": "mcr.microsoft.com/dotnet-buildtools/image-builder@sha256:05e5d23f0f7ebacf37cf1487f0a251158ca1031dd4833345b517e6d4b9611dc9",
              "baseImageDigest": "mcr.microsoft.com/windows/nanoserver@sha256:2b783310e6c82de737e893abd53ae238ca56b5a96e2861558fb9a111d6691ddb",
              "osType": "Windows",
              "osVersion": "Windows Server 2019",
              "architecture": "amd64",
              "created": "2020-09-15T17:10:11.3796277Z",
              "commitUrl": "https://github.com/dotnet/docker-tools/blob/38bc667d2578111c83d03e12bd90db3f11df3080/Dockerfile.windows"
            }
          ]
        }
      ]
    }
  ]
}
